capacities/__init__.py
capacities/api_client/__init__.py
capacities/api_client/client.py
capacities/api_client/models.py
capacities/bot/__init__.py
capacities/bot/telegram.py
capacities_python-0.1.2.dist-info/LICENSE.md
capacities_python-0.1.2.dist-info/METADATA
capacities_python-0.1.2.dist-info/WHEEL
capacities_python-0.1.2.dist-info/RECORD
